import_iphone_media/__init__.py
import_iphone_media/afc_utils.py
import_iphone_media/db.py
import_iphone_media/importer.py
import_iphone_media/main.py
import_iphone_media-0.1.1.dist-info/METADATA
import_iphone_media-0.1.1.dist-info/WHEEL
import_iphone_media-0.1.1.dist-info/entry_points.txt
import_iphone_media-0.1.1.dist-info/licenses/LICENSE
import_iphone_media-0.1.1.dist-info/RECORD
