Metadata-Version: 2.4
Name: import-iphone-media
Version: 0.1.1
Summary: Import photos and videos from your iPhone to your computer via USB. 
Project-URL: source, https://github.com/artificiadrian/import-iphone-media
Author-email: artificiadrian <adrian@artificiadrian.com>
License-File: LICENSE
Requires-Python: >=3.9
Requires-Dist: pymobiledevice3==4.21.1
Requires-Dist: rich==14.0.0
